wasatch/AbstractUSBDevice.py
wasatch/AndorDevice.py
wasatch/AreaScanImage.py
wasatch/AutoRaman.py
wasatch/AutoRamanRequest.py
wasatch/BLEDevice.py
wasatch/BalanceAcquisition.py
wasatch/CSVLoader.py
wasatch/CommandSettings.py
wasatch/ControlObject.py
wasatch/DetectorROI.py
wasatch/DetectorRegions.py
wasatch/DeviceFinderBLE.py
wasatch/DeviceFinderTCP.py
wasatch/DeviceFinderUSB.py
wasatch/DeviceID.py
wasatch/EEPROM.py
wasatch/EEPROM_multical.sav
wasatch/FPGAOptions.py
wasatch/FeatureIdentificationDevice.py
wasatch/FirmwareRequirements.py
wasatch/HardwareInfo.py
wasatch/IDSCamera.py
wasatch/IDSDevice.py
wasatch/IMX385.py
wasatch/InterfaceDevice.py
wasatch/MockUSBDevice.py
wasatch/OceanDevice.py
wasatch/PollStatus.py
wasatch/ProcessedReading.py
wasatch/ROI.py
wasatch/Reading.py
wasatch/RealUSBDevice.py
wasatch/SPIDevice.py
wasatch/SpectrometerRequest.py
wasatch/SpectrometerResponse.py
wasatch/SpectrometerSettings.py
wasatch/SpectrometerState.py
wasatch/StatusMessage.py
wasatch/TCPDevice.py
wasatch/TakeOneRequest.py
wasatch/WasatchBus.py
wasatch/WasatchDevice.py
wasatch/WasatchDeviceWrapper.py
wasatch/WrapperWorker.py
wasatch/__init__.py
wasatch/applog.py
wasatch/simulation_protocol.py
wasatch/utils.py
wasatch-2.3.6.dist-info/licenses/LICENSE
wasatch-2.3.6.dist-info/WHEEL
wasatch-2.3.6.dist-info/METADATA
wasatch-2.3.6.dist-info/RECORD
