Metadata-Version: 2.4
Name: wasatch
Version: 2.3.6
Summary: Application-level driver for Wasatch Photonics spectrometers
Requires-Python: >=3.9
License-File: LICENSE
Requires-Dist: numpy
Requires-Dist: six
Requires-Dist: psutil
Requires-Dist: future
Requires-Dist: pygtail
Requires-Dist: pyusb
Requires-Dist: requests
Requires-Dist: pexpect
Requires-Dist: seabreeze
Requires-Dist: pyudev
Requires-Dist: pywin32; platform_system=='Windows'
Requires-Dist: pyftdi
Requires-Dist: crcmod
Requires-Dist: bleak
Requires-Dist: ids_peak; platform_system=='Windows'
Project-URL: Homepage, https://github.com/WasatchPhotonics/wasatch.py
